bib2graph/__init__.py
bib2graph/analisis_red.py
bib2graph/consigue_los_articulos.py
bib2graph/enriquecimiento.py
bib2graph/models.py
bib2graph/queries.py
bib2graph-0.1.0.dist-info/entry_points.txt
bib2graph-0.1.0.dist-info/LICENSE
bib2graph-0.1.0.dist-info/METADATA
bib2graph-0.1.0.dist-info/WHEEL
bib2graph-0.1.0.dist-info/RECORD
