Metadata-Version: 2.1
Name: bib2graph
Version: 0.1.0
Summary: A Python package for bibliometric data processing and network analysis
Home-page: https://github.com/complexluise/bib2graph
License: Apache-2.0
Keywords: bibliometrics,network-analysis,citation-analysis,data-science,neo4j
Author: Luis Eduardo Higuera Calderon
Author-email: lhiguerac@unal.edu.co
Maintainer: Luis Eduardo Higuera Calderon
Maintainer-email: lhiguerac@unal.edu.co
Requires-Python: >=3.12,<4.0
Classifier: Development Status :: 4 - Beta
Classifier: Intended Audience :: Science/Research
Classifier: License :: OSI Approved :: Apache Software License
Classifier: Programming Language :: Python :: 3
Classifier: Programming Language :: Python :: 3.12
Classifier: Programming Language :: Python :: 3.13
Classifier: Topic :: Scientific/Engineering :: Information Analysis
Requires-Dist: bibtexparser (>=1.4.0,<2.0.0)
Requires-Dist: crossrefapi (>=1.5.0,<2.0.0)
Requires-Dist: elsapy (>=0.5.0,<0.6.0)
Requires-Dist: lxml (>=5.4.0,<6.0.0)
Requires-Dist: neomodel (>=5.4.5,<6.0.0)
Requires-Dist: networkx (>=3.1,<4.0)
Requires-Dist: pandas (>=2.0.0,<3.0.0)
Requires-Dist: pys2 (>=1.1.0,<2.0.0)
Requires-Dist: requests (>=2.31.0,<3.0.0)
Project-URL: Documentation, https://github.com/complexluise/bib2graph
Project-URL: Repository, https://github.com/complexluise/bib2graph
